thud/__init__.py
thud/cli.py
thud/constants.py
thud/utils.py
thud-0.1.0.dist-info/METADATA
thud-0.1.0.dist-info/WHEEL
thud-0.1.0.dist-info/entry_points.txt
thud-0.1.0.dist-info/top_level.txt
thud-0.1.0.dist-info/RECORD
