Metadata-Version: 2.4
Name: thud
Version: 0.1.0
Summary: Reactively change volume based on typing speed
Author-email: Paul Bokelman <paulbokelman.dev@gmail.com>
License: MIT
Requires-Python: >=3.12
Requires-Dist: osascript>=2020.12.3
Requires-Dist: pynput>=1.8.1
